odoo/addons/connector_pms_wubook/README.rst
odoo/addons/connector_pms_wubook/__init__.py
odoo/addons/connector_pms_wubook/__manifest__.py
odoo/addons/connector_pms_wubook/components/__init__.py
odoo/addons/connector_pms_wubook/components/adapter.py
odoo/addons/connector_pms_wubook/components/binder.py
odoo/addons/connector_pms_wubook/components/core.py
odoo/addons/connector_pms_wubook/components/deleter.py
odoo/addons/connector_pms_wubook/components/exporter.py
odoo/addons/connector_pms_wubook/components/importer.py
odoo/addons/connector_pms_wubook/components/listener.py
odoo/addons/connector_pms_wubook/components/mapper_export.py
odoo/addons/connector_pms_wubook/components/mapper_import.py
odoo/addons/connector_pms_wubook/controllers/__init__.py
odoo/addons/connector_pms_wubook/controllers/main.py
odoo/addons/connector_pms_wubook/data/cron.xml
odoo/addons/connector_pms_wubook/data/pms_data.xml
odoo/addons/connector_pms_wubook/data/queue_data.xml
odoo/addons/connector_pms_wubook/data/queue_job_function_data.xml
odoo/addons/connector_pms_wubook/models/__init__.py
odoo/addons/connector_pms_wubook/models/queue_job.py
odoo/addons/connector_pms_wubook/models/common/__init__.py
odoo/addons/connector_pms_wubook/models/common/backend.py
odoo/addons/connector_pms_wubook/models/common/backend_type.py
odoo/addons/connector_pms_wubook/models/common/backend_type_board_service.py
odoo/addons/connector_pms_wubook/models/common/backend_type_ota.py
odoo/addons/connector_pms_wubook/models/common/backend_type_room_type_class.py
odoo/addons/connector_pms_wubook/models/common/binding.py
odoo/addons/connector_pms_wubook/models/common/wubook_backend_journal_ota.py
odoo/addons/connector_pms_wubook/models/pms_availability/__init__.py
odoo/addons/connector_pms_wubook/models/pms_availability/adapter.py
odoo/addons/connector_pms_wubook/models/pms_availability/binder.py
odoo/addons/connector_pms_wubook/models/pms_availability/binding.py
odoo14_addon_connector_pms_wubook-14.0.1.0.1.dev132.dist-info/METADATA
odoo14_addon_connector_pms_wubook-14.0.1.0.1.dev132.dist-info/WHEEL
odoo14_addon_connector_pms_wubook-14.0.1.0.1.dev132.dist-info/top_level.txt
odoo14_addon_connector_pms_wubook-14.0.1.0.1.dev132.dist-info/RECORD
